PytableBox/PytableBox.py
PytableBox/__init__.py
PytableBox-1.0.2.dist-info/LICENCE.txt
PytableBox-1.0.2.dist-info/METADATA
PytableBox-1.0.2.dist-info/WHEEL
PytableBox-1.0.2.dist-info/top_level.txt
PytableBox-1.0.2.dist-info/RECORD
